justext/CHANGES
justext/LICENSE
justext/README
justext/__init__.py
justext/core.py
maalfrid_toolkit-1.4.4.dist-info/METADATA
maalfrid_toolkit-1.4.4.dist-info/WHEEL
maalfrid_toolkit-1.4.4.dist-info/entry_points.txt
maalfrid_toolkit-1.4.4.dist-info/licenses/LICENSE.txt
maalfrid_toolkit-1.4.4.dist-info/licenses/src/justext/LICENSE
maalfrid_toolkit/.directory
maalfrid_toolkit/__init__.py
maalfrid_toolkit/config.py
maalfrid_toolkit/crawl.py
maalfrid_toolkit/crawljobs/README.md
maalfrid_toolkit/crawljobs/example.com.yaml
maalfrid_toolkit/crawljobs/wget_warc.conf
maalfrid_toolkit/crawljobs/wget_warc.conf.example
maalfrid_toolkit/db.py
maalfrid_toolkit/htmlclean.py
maalfrid_toolkit/langdet.py
maalfrid_toolkit/logs/test-prefix_wget/test-prefix_wget-20250805_113010-39157aaf-e58b-498d-8021-7a85cd303fb1-banenor_no.jsonl
maalfrid_toolkit/models/README.md
maalfrid_toolkit/models/language_filter/unique_stop_words_nno.txt
maalfrid_toolkit/models/language_filter/unique_stop_words_nob.txt
maalfrid_toolkit/models/stoplists_justext/Albanian.txt
maalfrid_toolkit/models/stoplists_justext/Arabic.txt
maalfrid_toolkit/models/stoplists_justext/Armenian.txt
maalfrid_toolkit/models/stoplists_justext/Belarusian.txt
maalfrid_toolkit/models/stoplists_justext/Bengali.txt
maalfrid_toolkit/models/stoplists_justext/Bosnian.txt
maalfrid_toolkit/models/stoplists_justext/Bulgarian.txt
maalfrid_toolkit/models/stoplists_justext/Chinese_Cantonese.txt
maalfrid_toolkit/models/stoplists_justext/Chinese_Simplified.txt
maalfrid_toolkit/models/stoplists_justext/Chinese_Traditional.txt
maalfrid_toolkit/models/stoplists_justext/Croatian.txt
maalfrid_toolkit/models/stoplists_justext/Czech.txt
maalfrid_toolkit/models/stoplists_justext/Danish.txt
maalfrid_toolkit/models/stoplists_justext/Dutch.txt
maalfrid_toolkit/models/stoplists_justext/English.txt
maalfrid_toolkit/models/stoplists_justext/Esperanto.txt
maalfrid_toolkit/models/stoplists_justext/Estonian.txt
maalfrid_toolkit/models/stoplists_justext/Finnish.txt
maalfrid_toolkit/models/stoplists_justext/French.txt
maalfrid_toolkit/models/stoplists_justext/Georgian.txt
maalfrid_toolkit/models/stoplists_justext/German.txt
maalfrid_toolkit/models/stoplists_justext/Greek.txt
maalfrid_toolkit-1.4.4.dist-info/RECORD
