Metadata-Version: 2.4
Name: maalfrid_toolkit
Version: 1.4.4
Summary: Toolkit for the Målfrid project
Author-Email: Magnus Breder Birkenes <magnus.birkenes@nb.no>
License-File: LICENSE.txt
License-File: src/justext/LICENSE
Project-URL: repository, https://github.com/NationalLibraryOfNorway/maalfrid_toolkit
Requires-Python: <3.13,>=3.10
Requires-Dist: certifi==2024.8.30
Requires-Dist: charset-normalizer==3.4.0
Requires-Dist: faust-cchardet==2.1.19
Requires-Dist: gielladetect==1.0.3
Requires-Dist: html5lib==1.1
Requires-Dist: idna==3.10
Requires-Dist: lxml<=5.4.0
Requires-Dist: numpy==1.*
Requires-Dist: python-dateutil==2.9.0.post0
Requires-Dist: pytz==2024.2
Requires-Dist: requests==2.32.4
Requires-Dist: six==1.16.0
Requires-Dist: soupsieve==2.6
Requires-Dist: typing-extensions==4.12.2
Requires-Dist: tzdata==2024.2
Requires-Dist: urllib3<3.0,>=2.5.0
Requires-Dist: webencodings==0.5.1
Requires-Dist: pyyaml>=6.0.2
Requires-Dist: warcio>=1.7.4
Requires-Dist: psycopg2-binary>=2.9.10
Requires-Dist: PyMuPDF==1.23.26
Requires-Dist: pdfminer-six==20201018
Requires-Dist: sentence-splitter==1.4
Requires-Dist: joblib==1.4.2
Requires-Dist: tqdm>=4.67.1
Requires-Dist: python-docx>=1.1.2
Requires-Dist: docx2txt>=0.8
Requires-Dist: simhash>=2.1.2
Requires-Dist: python-dotenv>=1.0.1
Requires-Dist: htmldate>=1.9.3
Provides-Extra: glotlid
Requires-Dist: fasttext>=0.9.3; extra == "glotlid"
Requires-Dist: huggingface-hub>=0.26.3; extra == "glotlid"
